<?xml version="1.0" encoding="utf-8"?>
<!DOCTYPE hibernate-mapping PUBLIC "-//Hibernate/Hibernate Mapping DTD 3.0//EN"
"http://hibernate.sourceforge.net/hibernate-mapping-3.0.dtd">
<!-- 
    Mapping file autogenerated by MyEclipse Persistence Tools
-->
<hibernate-mapping>
    <class name="cn.daijia.vo.InfoCD" table="info_c_d" catalog="daijia">
        <id name="usernumber" type="java.lang.Integer">
            <column name="usernumber" />
            <generator class="identity" />
        </id>
        <property name="status" type="java.lang.Short">
            <column name="status" not-null="true">
                <comment>收/支方式</comment>
            </column>
        </property>
        <property name="payamount" type="java.lang.Double">
            <column name="payamount" precision="22" scale="0">
                <comment>发生金额</comment>
            </column>
        </property>
        <property name="paytime" type="java.lang.String">
            <column name="paytime" length="19">
                <comment>发生时间</comment>
            </column>
        </property>
        <property name="accountbalance" type="java.lang.Double">
            <column name="accountbalance" precision="22" scale="0">
                <comment>账户余额</comment>
            </column>
        </property>
        <property name="ordernumber" type="java.lang.Integer">
            <column name="ordernumber">
                <comment>关联订单编号</comment>
            </column>
        </property>
        <property name="remark" type="java.lang.String">
            <column name="remark">
                <comment>备注</comment>
            </column>
        </property>
    </class>
</hibernate-mapping>
